<rede id="ID2016405400">
                <p klasse="redner">
        <a id="r59"/>
        <redner id="11005081">
            <name>
                <vorname>Anke</vorname>
                <nachname>Hennig</nachname>
                <fraktion>SPD</fraktion>
            </name>
        </redner>Anke Hennig (SPD):</p>
                <p klasse="J_1">Sehr geehrte Frau Präsidentin! Sehr geehrte Kolleginnen und Kollegen! Liebe Zuhörende! Heute ist ein guter Tag. Ich würde sogar behaupten: Heute schreiben wir ein Stück Geschichte.</p>
                <kommentar>(Beifall bei der SPD und dem BÜNDNIS 90/DIE GRÜNEN sowie bei Abgeordneten der FDP)</kommentar>
                <p klasse="O">Mit der zweiten und dritten Lesung des Selbstbestimmungsgesetzes schaffen wir endlich nach über vier Jahrzehnten das unsägliche Transsexuellengesetz und seine menschenunwürdigen Praktiken ab.</p>
                <kommentar>(Nina Warken [CDU/CSU]: Sie hat scheinbar nicht zugehört!)</kommentar>
                <p klasse="O">Wir haben uns als Ampelkoalition dazu verpflichtet, das Selbstbestimmungsgesetz endlich möglich zu machen. Heute haben wir geliefert.</p>
                <kommentar>(Beifall bei der SPD sowie bei Abgeordneten des BÜNDNISSES 90/DIE GRÜNEN und der FDP)</kommentar>
                <p klasse="J">Ich habe es bereits in meiner ersten Rede gesagt und werde niemals müde, es immer wieder zu sagen: Das Selbstbestimmungsgesetz nimmt niemandem etwas weg. Ganz im Gegenteil: Es beseitigt Unrecht.</p>
                <kommentar>(Beifall bei der SPD und dem BÜNDNIS 90/DIE GRÜNEN sowie bei Abgeordneten der FDP)</kommentar>
                <p klasse="O">Ich sehe es als unsere Pflicht an, als Abgeordnete eines demokratischen Rechtsstaates dieses Unrecht zu beseitigen.</p>
                <p klasse="J">Bewusst gestreute Desinformationen und Hetze führen dazu, dass Misstrauen gesät und negative Emotionen gegenüber Transpersonen aufgebaut werden. Dabei hat all dies in der Debatte nichts verloren. Die negativen Auswirkungen dieser Debattenkultur treffen gerade die Jüngsten in unserer Gesellschaft, die feststellen, dass sie trans sind. Kinder und Jugendliche haben genauso wie Erwachsene ein Recht darauf, sich frei zu entfalten. Dazu zählt auch die geschlechtliche Identität.</p>
                <kommentar>(Beatrix von Storch [AfD]: Quatsch!)</kommentar>
                <p klasse="O">Deshalb haben wir sie in dem Gesetz auch bewusst mitgedacht.</p>
                <kommentar>(Beifall bei der SPD und dem BÜNDNIS 90/DIE GRÜNEN sowie der Abg. Katrin Helling-Plahr [FDP])</kommentar>
                <p klasse="J">In der Realität sind gerade Kinder oftmals Opfer von Mobbing. Es existieren böswillige Unwahrheiten, sie werden stigmatisiert, und ihr Umfeld kann oder will sie nicht angemessen unterstützen. Dass wir Kinder und Jugendliche im Selbstbestimmungsgesetz stärken, bedeutet auch, dass wir ihre Rechte stärken. Es wäre nach meiner Auffassung somit völlig folgerichtig, endlich Kinderrechte im Grundgesetz zu verankern.</p>
                <kommentar>(Beifall bei der SPD und dem BÜNDNIS 90/DIE GRÜNEN)</kommentar>
                <p klasse="J">Aus meiner praktischen Erfahrung als Kindertagespflegeperson kann ich Ihnen berichten, dass unsere Jüngsten es oftmals schon sehr früh wissen, wenn das ihnen zugewiesene Geschlecht nicht zu ihrer Identität passt. Ein Beispiel dazu: Ein Kind von sechs Jahren stellt sich bei mir in der Gruppe mit den Worten vor: Hallo Anke, mein Name ist Lara, aber eigentlich bin ich ein Junge.</p>
                <kommentar>(Zuruf der Abg. Beatrix von Storch [AfD])</kommentar>
                <p klasse="O">Mit dem Selbstbestimmungsgesetz können wir Kindern und Jugendlichen wie Lara einen Weg ermöglichen, den Personenstand und den Namen zu ändern, fernab von Angst, erniedrigenden Fragen und Zwangsbegutachtung.</p>
                <kommentar>(Beifall bei der SPD und dem BÜNDNIS 90/DIE GRÜNEN)</kommentar>
                <p klasse="J">Es ist notwendig, dass die Gesellschaft endlich alle Personen in ihrer Mitte akzeptiert, anstatt sie für ihre persönlichsten Entscheidungen zu verurteilen. Auch hier betone ich immer wieder gerne: Queeres Leben muss selbstverständlich sein.</p>
                <kommentar>(Beifall bei der SPD sowie bei Abgeordneten des BÜNDNISSES 90/DIE GRÜNEN)</kommentar>
                <p klasse="O">Ich werbe deshalb noch mal eindringlich um Ihre heutige Zustimmung zu diesem Gesetz.</p>
                <p klasse="J">Ich danke.</p>
                <kommentar>(Beifall bei der SPD und dem BÜNDNIS 90/DIE GRÜNEN sowie bei Abgeordneten der FDP)</kommentar>
                <name>Vizepräsidentin Petra Pau:</name>
                <p klasse="J_1">Das Wort hat der Abgeordnete Martin Reichardt für die AfD-Fraktion.</p>
                <kommentar>(Beifall bei der AfD)</kommentar>
            </rede>