<rede id="ID196808900">
        <p klasse="redner">
        <redner id="11004256">
            <name>
                <titel>Dr.</titel>
                <vorname>Karl-Heinz</vorname>
                <nachname>Brunner</nachname>
                <fraktion>SPD</fraktion>
            </name>
        </redner>Dr. Karl-Heinz Brunner (SPD):</p>
        <p klasse="J_1">Frau Präsidentin! Meine Damen! Meine Herren! Verehrte Zuhörerinnen und Zuhörer! Wäre es nicht so bitter, könnte man bei der Überschrift, die gewählt wurde, sagen: Sie wollen Vertrauen in die Richtigkeit richterlicher, staatsanwaltschaftlicher und behördlicher Entscheidungen herstellen – angeblich, um den Rechtsstaat zu stärken. Dann müsste man sagen: Schön, dass Sie in Deutschland angekommen sind; willkommen im Rechtsstaat!</p>
        <p klasse="J">Nach Religion, Minderheiten, Schwulen und Lesben und Ihrem Lieblingsthema, den Flüchtlingen, soll es nun der Rechtsstaat sein, an den Hand gelegt wird.</p>
        <kommentar>(Stephan Brandner [AfD]: Och nee! Herr Brunner!)</kommentar>
        <p klasse="O">Ich könnte jetzt sagen, dass der erste Blick täuscht. Nun ja, lassen Sie uns doch mal schauen, von wem diese Debatte angestoßen wird: von einem Ex-Staatsanwalt, der seinen Beamtenstatus verloren hat, da er die Pflicht zur Verfassungstreue verletzt hat, indem er den deutschen Staat, für den auch wir hier stehen, als „Unterdrückungsinstrument“ bezeichnete;</p>
        <kommentar>(Stephan Brandner [AfD]: Herr Brunner, Sie verwechseln da was!)</kommentar>
        <p klasse="O">von einer ehemaligen Richterin, die in ihrer Rede behauptet, dass dem Gesundheitssystem Milliardenkosten entstünden, weil Flüchtlinge ihre Beipackzettel nicht lesen könnten – ein Faktencheck zeigt: die Behauptung ist dreist konstruiert –; von einem Ex-Oberstaatsanwalt, der sagt – ich zitiere –: „Wenn die Blockparteien so weitermachen können wie bisher, dann hat unser Land in 20 Jahren fertig, wir wären wirtschaftlich ruiniert, von einer nicht-deutschen Mehrheit besiedelt und auf dem besten Weg in die islamische Republik“;</p>
        <kommentar>(Matthias W. Birkwald [DIE LINKE]: Völkischer Unsinn!)</kommentar>
        <p klasse="O">oder von einem Ex-Richter am Landgericht, der sich solche rassistischen Äußerungen wie „kleiner Halbneger“ erlaubt.</p>
        <kommentar>(Abg. Jens Maier [AfD] meldet sich zu einer Zwischenfrage)</kommentar>
        <p klasse="J">Ist das das Vertrauen, das Sie in den Rechtsstaat herstellen wollen? Mit den Unterzeichnern gelingt Ihnen dies jedenfalls nicht.</p>
        <kommentar>(Beifall bei Abgeordneten der SPD, der CDU/CSU und der FDP)</kommentar>
        <p klasse="J">Zugegeben: Es gibt Gerichtsurteile, die große öffentliche Aufmerksamkeit auf sich ziehen: das Wegsperren des Herrn Mollath, der Prozess gegen Uli Hoeneß. Die öffentliche Meinung und die Entscheidungen klaffen auseinander. Sie befördern öffentliche Zweifel an der Justiz, ihrer Unabhängigkeit und ihrem Realitätssinn. Ja, Zweifel! Doch dies war schon immer so, und es wird immer so sein; denn dafür haben wir unser Recht, ein geschriebenes Recht, ein Recht, das nicht Stimmungen, nicht dem Gefühl der Straße, nicht der öffentlichen Meinung oder gar dem Volksempfinden nachgibt.</p>
        <kommentar>(Beifall der Abg. Dr. Manuela Rottmann [BÜNDNIS 90/DIE GRÜNEN])</kommentar>
        <p klasse="O">Wer daraus jedoch Reformbedarf bei der Bundesrichterwahl konstruiert, der hat unser Rechtssystem, jedenfalls das der Bundesrepublik Deutschland, nicht verstanden.</p>
        <kommentar>(Beifall bei der SPD sowie bei Abgeordneten der CDU/CSU, der FDP, der LINKEN und des BÜNDNISSES 90/DIE GRÜNEN)</kommentar>
        <p klasse="J">Meine Damen und Herren, denn so kritisch diese Urteile in der Gesellschaft aufgenommen wurden: Es ist nicht zu erkennen, dass sie das Grundvertrauen in die deutsche Justiz erschüttern.</p>
        <name>Vizepräsidentin Claudia Roth:</name>
        <p klasse="J_1">Herr Kollege, eine Sekunde. – Ich will ankündigen, dass ich heute angesichts der langen Tagesordnung, die wir noch vor uns haben, und angesichts der Verantwortung, die wir nicht nur gegenüber uns selber haben, sondern auch gegenüber den Mitarbeiterinnen und Mitarbeitern des Hauses, der Verwaltung, unseren Protokollanten, unseren Parlamentsassistenten, dem Personal des Restaurants, keine Zwischenfragen und keine Kurzinterventionen mehr zulasse.</p>
        <kommentar>(Beifall bei Abgeordneten der LINKEN und des BÜNDNISSES 90/DIE GRÜNEN)</kommentar>
        <p klasse="redner">
        <redner id="11004256">
            <name>
                <titel>Dr.</titel>
                <vorname>Karl-Heinz</vorname>
                <nachname>Brunner</nachname>
                <fraktion>SPD</fraktion>
            </name>
        </redner>Dr. Karl-Heinz Brunner (SPD):</p>
        <p klasse="J_1">Vielen Dank, Frau Präsidentin. – Dies wird im Übrigen entgegen der ganzen politischen Schaumschlägerei vonseiten der AfD hier durch statistische Daten belegt. Die Frage „Wie sehr vertrauen Sie der Justiz bzw. dem deutschen Rechtssystem?“ haben 72 Prozent mit „Eher vertrauen“ beantwortet, und die Tendenz ist steigend.</p>
        <p klasse="J">Das hat seinen Grund. Er heißt auch: demokratische Legitimation, die Legitimation, die sich mit der Parlamentsbeteiligung bei der Richterwahl bewährt, die Legitimation, die Hauptmotiv für die Regelungen zur Rich­terwahl war: ja, auch für eine aufgrund ihrer Verstrickung in die Nazigewaltherrschaft diskreditierte Justiz in der Bevölkerung wieder Vertrauen herzustellen. Übrigens: Die Lektüre der „Akte Rosenburg“ dazu hilft Ihnen da weiter.</p>
        <p klasse="J">Noch dazu, meine Damen und Herren, dienen die Richterwahlen ja auch dem Zweck, die Kandidatinnen und Kandidaten für ein Richteramt auf ihre Eignung zu prüfen, nicht allein nach ihrer Platzziffer und juristischen Brillanz, sondern vor allen Dingen hinsichtlich ihrer Verfassungstreue.</p>
        <p klasse="J">Deshalb, meine Damen und Herren, lassen Sie uns beim bewährten Prozedere verbleiben! Um den Rechtsstaat zu stärken, braucht es mehr, nämlich eine gute Ausstattung mit Richtern, Staatsanwälten, Rechtspflegern, Amtsanwälten und engagierten Justizbediensteten, die allesamt fest und unverrückbar dort stehen, wo sie hingehören: auf dem Boden unseres Grundgesetzes.<a id="S7815" name="S7815" typ="druckseitennummer"/>
    </p>
        <p klasse="J">Herzlichen Dank.</p>
        <kommentar>(Beifall bei der SPD sowie bei Abgeordneten der CDU/CSU und des BÜNDNISSES 90/DIE GRÜNEN und des Abg. Dr. Jürgen Martens [FDP])</kommentar>
        <name>Vizepräsidentin Claudia Roth:</name>
        <p klasse="J_1">Vielen Dank, Kollege Brunner. – So, es gibt jetzt keine Zwischenfrage und keine Kurzintervention. Aber nach § 30 unserer Geschäftsordnung hat Herr Maier kurz das Wort.</p>
        <kommentar>(Canan Bayram [BÜNDNIS 90/DIE GRÜNEN]: Persönliche Erklärung: Ich habe keine Twitter-Nachricht geschrieben!)</kommentar>
      </rede>