<rede id="ID209113900">
				<p klasse="redner">
					<redner id="11004754">
						<name>
							<titel>Dr.</titel>
							<vorname>Gero Clemens</vorname>
							<nachname>Hocker</nachname>
							<fraktion>FDP</fraktion>
						</name>
					</redner>Dr. Gero Clemens Hocker (FDP):</p>
				<p klasse="J_1">Verehrte Frau Präsidentin! Liebe Kolleginnen und Kollegen! Die Zahl der Ernährungstrends ist wahrscheinlich von niemandem wirklich mal wissenschaftlich endgültig ermittelt worden. Es gibt Frutarier, es gibt Paleo, es gibt Veganer und Vegetarier sowieso. Für Mediziner ist klar: Vor allem die Ausgewogenheit der Ernährung ist entscheidend dafür, wie gesund sie ist.</p>
				<p klasse="J">Meine sehr verehrten Damen und Herren, die Menschen da draußen brauchen am allerwenigsten</p>
				<kommentar>(Stephan Brandner [AfD]: … die FDP)</kommentar>
				<p klasse="O">die Politiker, die ihnen vorschreiben könnten oder mögen, wie sie sich zu ernähren haben. Das zu entscheiden, ist die ureigene Aufgabe eines jeden Menschen in dieser Gesellschaft. Ich sage es ganz ausdrücklich: Wenn es nach Ihnen ginge, dann gäbe es in Deutschland täglich in den Kantinen, in den Mensen verpflichtend Bauchspeck, und dann würden die Kinder noch mit Lebertran großgezogen werden.</p>
				<kommentar>(Heiterkeit und Beifall bei Abgeordneten der FDP, der SPD, des BÜNDNISSES 90/DIE GRÜNEN und der LINKEN)</kommentar>
				<p klasse="O">Und das ist ganz bestimmt nicht die Vision für das Jahr 2023.</p>
				<kommentar>(Beifall bei der FDP sowie bei Abgeordneten der SPD, des BÜNDNISSES 90/DIE GRÜNEN und der LINKEN – Abg. Norbert Kleinwächter [AfD] meldet sich zu einer Zwischenfrage)</kommentar>
				<p klasse="O">– Ich bitte, die Zwischenfrage zuzulassen, wenn das geht. Ich brenne darauf, Frau Präsidentin.</p>
				<name>Vizepräsidentin Aydan Özoğuz:</name>
				<p klasse="J_1">Dann machen wir das auch. – Bitte schön.</p>
				<p klasse="redner">
					<redner id="11004754">
						<name>
							<titel>Dr.</titel>
							<vorname>Gero Clemens</vorname>
							<nachname>Hocker</nachname>
							<fraktion>FDP</fraktion>
						</name>
					</redner>Dr. Gero Clemens Hocker (FDP):</p>
				<p klasse="J_1">Ja, bitte.</p>
				<p klasse="redner">
					<redner id="11004781">
						<name>
							<vorname>Norbert</vorname>
							<nachname>Kleinwächter</nachname>
							<fraktion>AfD</fraktion>
						</name>
					</redner>Norbert Kleinwächter (AfD):</p>
				<p klasse="J_1">Vielen Dank, Frau Präsidentin. – Herr Dr. Hocker, es geht hier jetzt ja um die Kennzeichnung von Insekten in Lebensmitteln. Die Kantine ist ein sehr, sehr gutes Beispiel. Die Leute bekommen dort eben nicht erst lange Zutatenlisten zum Lesen vorgelegt, um zu wissen, ob im Essen Käfer, Mehlwürmer oder andere Bestandteile enthalten sind, die diese Menschen nicht essen wollen. Uns geht es hier erst mal um Verpackungen und eine eindeutige große Kennzeichnung.</p>
				<kommentar>(Renate Künast [BÜNDNIS 90/DIE GRÜNEN]: Größer als das ganze Schild!)</kommentar>
				<p klasse="J">Das ist ja nicht neu. Es gibt ja auch ein Vegansymbol, es gibt ein Schweinefleischsymbol, es gibt ein Rindfleischsymbol. Was ist so schwer daran, die Leute darüber zu informieren, dass sie im Begriff sein werden, ein Insekt zu futtern?</p>
				<kommentar>(Beifall bei der AfD – Dr. Marie-Agnes Strack-Zimmermann [FDP]: Ein bisschen Eiweiß würde Ihnen guttun!)</kommentar>
				<p klasse="redner">
					<redner id="11004754">
						<name>
							<titel>Dr.</titel>
							<vorname>Gero Clemens</vorname>
							<nachname>Hocker</nachname>
							<fraktion>FDP</fraktion>
						</name>
					</redner>Dr. Gero Clemens Hocker (FDP):</p>
				<p klasse="J_1">Mit manchen Fragen, verehrter Herr Kollege, entlarvt man sich selbst. Ich sage mal ganz ehrlich: Es gibt auch kein Symbol für blöde Vorschläge in der Politik.</p>
				<kommentar>(Beifall bei Abgeordneten der FDP, der SPD und der LINKEN – Stephan Brandner [AfD]: Wenn FDP draufsteht, weiß man schon, was für ein Blödsinn drinsteht! Das gibt es schon!)</kommentar>
				<p klasse="O">Das ist manchmal bedauerlich; aber das wäre vielleicht auch eine Form der Verbraucher- oder auch der Wählertäuschung.</p>
				<p klasse="J">Ich sage Ihnen ganz ausdrücklich: Es ist nicht auszuschließen, dass bestimmte Reststoffe von Insekten in bestimmten Lebensmitteln vorhanden sind. Aber ich sage Ihnen eins: Die Menschen da draußen sind schlau genug, um zu wissen, dass in etwas, was unter freiem Himmel groß geworden, gewachsen ist, natürlich Reststoffe drin sein können. Deswegen entlarvt diese Frage sehr deutlich, dass es Ihnen nur um Populismus und darum geht, irgendwelche Ängste zu erzeugen, die die Menschen da draußen ohne Sie gar nicht hätten. Das scheint Ihr Prinzip bei der AfD zu sein; aber damit kommen Sie bei uns nicht durch.</p>
				<kommentar>(Beifall bei Abgeordneten der FDP – Martin Reichardt [AfD]: Wenn einer populistisch ist, dann sind Sie das doch! Sie sind doch politisch am Ende! Bei Populismus sind Sie ganz vorne dabei!)</kommentar>
				<p klasse="O">– Wollen Sie noch eine Frage stellen? Dann trauen Sie sich, dann nur zu!</p>
				<kommentar>(Martin Reichardt [AfD]: Nein, keine Frage!)</kommentar>
				<p klasse="O">– Schade.</p>
				<kommentar>(Martin Reichardt [AfD]: Sie geben ja auch nur blöde Antworten! Was soll man dann noch eine Frage stellen?)</kommentar>
				<name>Vizepräsidentin Aydan Özoğuz:</name>
				<p klasse="J_1">Nein, jetzt machen Sie mal weiter.</p>
				<p klasse="redner">
					<redner id="11004754">
						<name>
							<titel>Dr.</titel>
							<vorname>Gero Clemens</vorname>
							<nachname>Hocker</nachname>
							<fraktion>FDP</fraktion>
						</name>
					</redner>Dr. Gero Clemens Hocker (FDP):</p>
				<p klasse="J_1">Man entlarvt sich am besten selbst.</p>
				<p klasse="J">Meine sehr verehrten Damen und Herren, Fakt ist, dass die Landwirtschaft sich seit Jahrtausenden immer gewandelt hat, immer effizienter geworden ist, auf Herausforderungen reagiert hat. Aktuell haben wir die Situation, dass sich die Landwirtschaft durch die Versiegelung von Flächen und eine Vielzahl anderer Faktoren – Energiewende; Windkraftanlagen werden gebaut; Fundamente werden errichtet und viele andere Dinge mehr – wandeln muss. Sie muss effizienter werden, und das ist sie seit Jahrtausenden geworden. Es gehört auch dazu: Wenn die Bevölkerungszahlen auf diesem Planeten weiterhin explodieren – davon ist auszugehen –, müssen wir uns neue Möglichkeiten erschließen, um die Ernährung der Menschen – gerade auch in ärmeren Regionen dieses Globusses – sicherzustellen.</p>
				<p klasse="J">Man hat über Jahrzehnte, Jahrhunderte Züchtungsmethoden entwickelt, hat die Dinge immer effizienter und schmackhafter gemacht. Es gibt, ehrlicherweise gesagt, überhaupt keinen nachvollziehbaren Grund, warum man nicht auch den Zugang zu Insekten ermöglichen können sollte, wenn das der Wunsch des Verbrauchers ist, und das ist ganz bestimmt nicht abhängig davon, was Sie gut oder was Sie schlecht finden.</p>
				<kommentar>(Beifall bei Abgeordneten der FDP und der SPD)</kommentar>
				<p klasse="J">Ich sage Ihnen auch: Das, was Sie hier manchmal zum Besten geben – da waren Sie eben wieder das beste Beispiel –, das ist häufig genug unappetitlich, das ist häufig genug schwer verdaulich.</p>
				<kommentar>(Stephan Brandner [AfD]: Sie triefen ja vor Hass, Herr Hocker!)</kommentar>
				<p klasse="O">Ich sage Ihnen aber auch, meine sehr verehrten Kolleginnen und Kollegen von der AfD: Sie können hier einbringen, was Sie wollen. Niemand wird Ihnen das jemals irgendwie abspenstig machen oder ausreden wollen. Aber dann überlassen Sie es doch bitte schön auch den Menschen selber, für sich zu entscheiden, wie sie sich zu ernähren haben, und spielen Sie sich da nicht irgendwie als der Lehrmeister auf!</p>
				<kommentar>(Martin Reichardt [AfD]: Das sagen Sie von der Ampel, die den Menschen alles verbieten will!)</kommentar>
				<p klasse="J">Meine sehr verehrten Damen und Herren, es gibt gesellschaftliche Kräfte – ich denke an Extinction Rebellion und andere –,</p>
				<kommentar>(Stephan Brandner [AfD]: Und die ARD!)</kommentar>
				<p klasse="O">die den Menschen gerne vorschreiben wollen, wie sie sich zu ernähren haben, die ihnen gerne den Appetit und die Lust auf Fleisch nehmen wollen, auf das Kotelett, auf das Schnitzel. Ist Ihnen eigentlich bewusst, wie sehr Sie sich gerade mit solchen Kräften gemeinmachen, wenn Sie an einer anderen Stelle des Ernährungssystems den Menschen Vorschriften machen wollen?</p>
				<kommentar>(Martin Reichardt [AfD]: Sie haben es immer noch nicht verstanden! Es geht um die Kennzeichnung!)</kommentar>
				<p klasse="J">Wir glauben daran, dass die urpersönliche Entscheidung des Verbrauchers in seine Hände gehört, dass er schlau genug ist und es besser weiß als jeder andere, worauf er Appetit hat und was er essen möchte.</p>
				<kommentar>(Norbert Kleinwächter [AfD]: Deshalb muss man es doch kennzeichnen!)</kommentar>
				<p klasse="O">In diesem Sinne werden wir auch die Zukunft in Deutschland gestalten.</p>
				<p klasse="J">Vielen Dank.</p>
				<kommentar>(Beifall bei Abgeordneten der FDP, der SPD und des BÜNDNISSES 90/DIE GRÜNEN – Stephan Brandner [AfD]: Um Gottes willen! – Martin Reichardt [AfD]: Ihre Zeit läuft doch ab!)</kommentar>
				<name>Vizepräsidentin Aydan Özoğuz:</name>
				<p klasse="J_1">Nächster Redner ist Martin Sichert von der AfD-Fraktion.</p>
				<kommentar>(Beifall bei der AfD)</kommentar>
			</rede>