<rede id="ID195103900">
        <p klasse="redner">
        <redner id="11004067">
            <name>
                <vorname>Katja</vorname>
                <nachname>Keul</nachname>
                <fraktion>BÜNDNIS 90/DIE GRÜNEN</fraktion>
            </name>
        </redner>Katja Keul (BÜNDNIS 90/DIE GRÜNEN):</p>
        <p klasse="J_1">Vielen Dank, Herr Präsident. – Meine Frage an die Bundesregierung bezieht sich auf die Brandkatastrophe in Niedersachsen, die durch die Bundeswehr am 3. September verursacht worden ist. Der Brand dauert ja noch an. Die neueste Information, die wir jetzt haben, ist, dass dort offensichtlich gar nicht die Bundeswehr das Gerät testet, sondern dass die Industrie dort selber schießt. Deswegen fragt sich jetzt, nachdem wir uns längere Zeit mit den Abläufen beschäftigt haben, schon noch mal: Welchen Einfluss hat denn eigentlich die Industrie und welchen hat die Wehrtechnische Dienststelle, wenn es darum geht, solche Beschusstests freizugeben? Das wäre, glaube ich, auch für alle Betroffenen sehr interessant.</p>
        <p klasse="redner">
        <redner id="11003638">
            <name>
                <vorname>Jens</vorname>
                <nachname>Spahn</nachname>
                <rolle>
                    <rolle_lang>Bundesminister für Gesundheit</rolle_lang>
                    <rolle_kurz>Bundesminister BMG</rolle_kurz>
                </rolle>
            </name>
        </redner>Jens Spahn, Bundesminister für Gesundheit:</p>
        <p klasse="J_1">Herr Präsident, der Herr Kollege Staatssekretär Silberhorn ist zur Antwort bereit.</p>
        <name>Präsident Dr. Wolfgang Schäuble:</name>
        <p klasse="J_1">Herr Staatssekretär.</p>
      </rede>